lowhaio_aws_sigv4.py
lowhaio_aws_sigv4-0.0.4.dist-info/LICENSE
lowhaio_aws_sigv4-0.0.4.dist-info/METADATA
lowhaio_aws_sigv4-0.0.4.dist-info/WHEEL
lowhaio_aws_sigv4-0.0.4.dist-info/top_level.txt
lowhaio_aws_sigv4-0.0.4.dist-info/RECORD
