Metadata-Version: 2.1
Name: lowhaio-aws-sigv4
Version: 0.0.4
Summary: AWS Signature Version 4 signing for lowhaio
Home-page: https://github.com/michalc/lowhaio-aws-sigv4
Author: Michal Charemza
Author-email: michal@charemza.name
License: UNKNOWN
Platform: UNKNOWN
Classifier: Programming Language :: Python :: 3
Classifier: License :: OSI Approved :: MIT License
Classifier: Operating System :: OS Independent
Classifier: Framework :: AsyncIO
Requires-Python: >=3.6.0
